{
    "Hand-Pulled Noodles (Biang-Biang Noodles)" :[
        {
            "Name": "Cumin Lamb In Sauce",
            "Price": 12.99,
            "img": ""
        },
        {
            "Name": "Cumin Lamb In Soup",
            "Price": 12.99,
            "img": ""
        },
        {
            "Name": "Pork 'Zha Jiang' In Sauce",
            "Price": 12.99,
            "img": ""
        },
        {
            "Name": "Oil Seared In Sauce",
            "Price": 12.99,
            "img": ""
        },
        {
            "Name": "Stewed Pork In Soup",
            "Price": 12.99,
            "img": ""
        },
        {
            "Name": "Tingly Beef In Sauce",
            "Price": 12.99,
            "img": ""
        },
        {
            "Name": "Tingly Beef In Soup",
            "Price": 12.99,
            "img": ""
        },
        {
            "Name": "Curry Beef In Sauce",
            "Price": 12.99,
            "img": ""
        },
        {
            "Name": "Mixed Vegi in Sauce",
            "Price": 12.99,
            "img": ""
        }
    ],
    "Noodles": [
        {
            "Name": "Pork 'Zha Jiang' Noodle",
            "Price": 12.99,
            "img": ""
        },
        {
            "Name": "Dandan Noodle",
            "Price": 12.99,
            "img": ""
        },
        {
            "Name": "Beef Noodles In Soup",
            "Price": 12.99,
            "img": ""
        },
        {
            "Name": "Cumin Lamb Noodle In Soup",
            "Price": 12.99,
            "img": ""
        },
        {
            "Name": "Spicy & Sour Vermicelli",
            "Price": 12.99,
            "img": ""
        },
        {
            "Name": "Beef Vermichelli",
            "Price": 12.99,
            "img": ""
        }
    ],
    "Dumplings":[
        {
            "Name": "Pork Dumplings In Sauce",
            "Price": 12.99,
            "img": ""
        },
        {
            "Name": "Pork Dumplings In Soup",
            "Price": 12.99,
            "img": ""
        },
        {
            "Name": "Lamb Dumplings In Sauce",
            "Price": 12.99,
            "img": ""
        },
        {
            "Name": "Lamb Dumplings In Soup",
            "Price": 12.99,
            "img": ""
        },
        {
            "Name": "Spinich Dumplings In Sauce",
            "Price": 12.99,
            "img": ""
        },
        {
            "Name": "Spinisch Dumplings In Soup",
            "Price": 12.99,
            "img": ""
        }
    ],
    "Rou Jia Mo":[
        {
            "Name": "Stewed Pork Burger",
            "Price": 4.99
        },
        {
            "Name":"Cumin Lamb Burger",
            "Price": 4.99
        }

    ],
    "Cold Noodles":
                [
                    {
                        "Name": "Liang Pi",
                        "Price": 9.00
                    },
                    {
                        "Name": "Stir-fried Liang-Pi",
                        "Price": 9.00
                    }
                ],
    "Salad":[
                
                    {
                        "Name" : "Spicy Cumumber Salad",
                        "Price": 6.0
                    },
                    {
                        "Name": "Tiger Salad",
                        "Price": 8.00
                    }
            ]

}